dyntastic/__init__.py
dyntastic/attr.py
dyntastic/batch.py
dyntastic/exceptions.py
dyntastic/main.py
dyntastic/py.typed
dyntastic/pydantic_compat.py
dyntastic/transact.py
dyntastic-0.18.0.dist-info/licenses/LICENSE
dyntastic-0.18.0.dist-info/METADATA
dyntastic-0.18.0.dist-info/WHEEL
dyntastic-0.18.0.dist-info/top_level.txt
dyntastic-0.18.0.dist-info/RECORD
