Metadata-Version: 2.4
Name: dyntastic
Version: 0.18.0
Summary: A DynamoDB library on top of Pydantic and boto3.
Home-page: https://github.com/nayaverdier/dyntastic
Author: Naya Verdier
License: MIT
Classifier: Programming Language :: Python
Classifier: Programming Language :: Python :: 3
Requires-Python: >=3.7
License-File: LICENSE
Requires-Dist: boto3>=1.10.0; python_version < "3.12"
Requires-Dist: boto3>=1.20.0; python_version >= "3.12"
Requires-Dist: pydantic<3,>=1.7.1
Requires-Dist: importlib-metadata>=1.0.0; python_version < "3.8"
Provides-Extra: dev
Requires-Dist: black; extra == "dev"
Requires-Dist: boto3-stubs[dynamodb]; extra == "dev"
Requires-Dist: coverage; extra == "dev"
Requires-Dist: flake8==6.0.0; python_version > "3.7" and extra == "dev"
Requires-Dist: flake8<5; python_version == "3.7" and extra == "dev"
Requires-Dist: flake8-bugbear; extra == "dev"
Requires-Dist: isort; extra == "dev"
Requires-Dist: moto==4.2.2; extra == "dev"
Requires-Dist: mypy; extra == "dev"
Requires-Dist: pre-commit; extra == "dev"
Requires-Dist: pytest; extra == "dev"
Requires-Dist: pytest-cov; extra == "dev"
Requires-Dist: pytest-mock; extra == "dev"
Requires-Dist: pytest-sugar; extra == "dev"
Requires-Dist: pytest-xdist; extra == "dev"
Provides-Extra: deploy
Requires-Dist: twine; extra == "deploy"
Dynamic: author
Dynamic: classifier
Dynamic: description
Dynamic: description-content-type
Dynamic: home-page
Dynamic: license
Dynamic: license-file
Dynamic: provides-extra
Dynamic: requires-dist
Dynamic: requires-python
Dynamic: summary
